contain_101_or_not/__init__.py
contain_101_or_not/checker.py
contain_101_or_not-1.1.0.dist-info/licenses/LICENSE
contain_101_or_not-1.1.0.dist-info/METADATA
contain_101_or_not-1.1.0.dist-info/WHEEL
contain_101_or_not-1.1.0.dist-info/top_level.txt
contain_101_or_not-1.1.0.dist-info/RECORD
