Metadata-Version: 2.4
Name: contain_101_or_not
Version: 1.1.0
Summary: Check if a binary string contains 101 using DFA
Author: Mohamed Khaled
Author-email: Mohamed khaled <mokhaled732003@gmail.com>
Requires-Python: >=3.6
License-File: LICENSE
Dynamic: author
Dynamic: license-file
Dynamic: requires-python
